ph_utils/__init__.py
ph_utils/common.py
ph_utils/config.py
ph_utils/crypto.py
ph_utils/date.py
ph_utils/id.py
ph_utils/logger.py
ph_utils-0.1.1.dist-info/WHEEL
ph_utils-0.1.1.dist-info/METADATA
ph_utils-0.1.1.dist-info/RECORD
