Metadata-Version: 2.3
Name: ph-utils
Version: 0.1.1
Summary: The python3 tool classes
Author: Tenny
Author-email: Tenny <tenny.shu@foxmail.com>
License: MulanPSL-2.0
Classifier: Programming Language :: Python :: 3.10
Classifier: License :: OSI Approved :: Mulan Permissive Software License v2 (MulanPSL-2.0)
Classifier: Operating System :: OS Independent
Requires-Python: >=3.10
Project-URL: Bug Tracker, https://gitee.com/towardly/ph-utils_py/issues
Project-URL: Homepage, https://gitee.com/towardly/ph-utils_py
